odoo/addons/payment_bacen_pix/README.rst
odoo/addons/payment_bacen_pix/__init__.py
odoo/addons/payment_bacen_pix/__manifest__.py
odoo/addons/payment_bacen_pix/controllers/__init__.py
odoo/addons/payment_bacen_pix/controllers/main.py
odoo/addons/payment_bacen_pix/data/payment_acquirer_data.xml
odoo/addons/payment_bacen_pix/data/payment_icon_data.xml
odoo/addons/payment_bacen_pix/i18n/payment_bacen_pix.pot
odoo/addons/payment_bacen_pix/models/__init__.py
odoo/addons/payment_bacen_pix/models/payment_acquirer.py
odoo/addons/payment_bacen_pix/models/payment_transaction.py
odoo/addons/payment_bacen_pix/readme/CONTRIBUTORS.rst
odoo/addons/payment_bacen_pix/readme/DESCRIPTION.rst
odoo/addons/payment_bacen_pix/readme/INSTALL.rst
odoo/addons/payment_bacen_pix/static/description/icon.png
odoo/addons/payment_bacen_pix/static/description/index.html
odoo/addons/payment_bacen_pix/static/img/bacen.png
odoo/addons/payment_bacen_pix/static/img/pix.png
odoo/addons/payment_bacen_pix/tests/__init__.py
odoo/addons/payment_bacen_pix/tests/test_bacen_pix.py
odoo/addons/payment_bacen_pix/tests/fixtures/test_pix_bacen.yaml
odoo/addons/payment_bacen_pix/tests/fixtures/test_pix_bacen_fail_token.yaml
odoo/addons/payment_bacen_pix/views/payment_transfer_templates.xml
odoo/addons/payment_bacen_pix/views/payment_views.xml
odoo14_addon_payment_bacen_pix-14.0.1.1.0.dist-info/METADATA
odoo14_addon_payment_bacen_pix-14.0.1.1.0.dist-info/WHEEL
odoo14_addon_payment_bacen_pix-14.0.1.1.0.dist-info/top_level.txt
odoo14_addon_payment_bacen_pix-14.0.1.1.0.dist-info/RECORD
